pyfinidash/__init__.py
pyfinidash/__main__.py
pyfinidash/pyfinidash.py
pyfinidash-0.1.0.dist-info/METADATA
pyfinidash-0.1.0.dist-info/WHEEL
pyfinidash-0.1.0.dist-info/entry_points.txt
pyfinidash-0.1.0.dist-info/top_level.txt
pyfinidash-0.1.0.dist-info/RECORD
