Metadata-Version: 2.1
Name: pyfinidash
Version: 0.1.0
Summary: A simple-to-use wrapper over the AWS Infinidash API
Home-page: https://github.com/cmstead/pyfinidash#readme
Author: Chris Stead
Author-email: cmstead@gmail.com
License: MIT
Platform: any
Classifier: Programming Language :: Python :: 3
